{
  "id": "feature",
  "type": "SharedSlice",
  "name": "Features",
  "description": "Feature",
  "variations": [
    {
      "id": "default",
      "name": "Default",
      "docURL": "...",
      "version": "initial",
      "description": "Default",
      "imageUrl": "",
      "primary": {
        "sub_heading": {
          "type": "StructuredText",
          "config": {
            "label": "Sub Heading",
            "placeholder": "",
            "allowTargetBlank": false,
            "single": "heading3,heading4"
          }
        },
        "heading": {
          "type": "StructuredText",
          "config": {
            "label": "Heading",
            "placeholder": "",
            "allowTargetBlank": false,
            "single": "heading2"
          }
        }
      },
      "items": {
        "icon": {
          "type": "Text",
          "config": {
            "label": "Icon",
            "placeholder": "Copy the icon name from https://lucide.dev"
          }
        },
        "title": {
          "type": "Text",
          "config": {
            "label": "title",
            "placeholder": ""
          }
        },
        "description": {
          "type": "Text",
          "config": {
            "label": "description",
            "placeholder": ""
          }
        }
      }
    }
  ]
}
